webdriver_extended/__init__.py
webdriver_extended/chrome/__init__.py
webdriver_extended/chrome/webdriver.py
webdriver_extended/chrome/webelement.py
webdriver_extended-2.0.1.dist-info/LICENSE
webdriver_extended-2.0.1.dist-info/METADATA
webdriver_extended-2.0.1.dist-info/WHEEL
webdriver_extended-2.0.1.dist-info/RECORD
